setup.py
junkeldat/__init__.py
somsomsom.egg-info/PKG-INFO
somsomsom.egg-info/SOURCES.txt
somsomsom.egg-info/dependency_links.txt
somsomsom.egg-info/top_level.txt