Metadata-Version: 1.0
Name: somsomsom
Version: 1.0
Summary: The junkeldat software
Home-page: http://pypi.python.org/pypi/junkeldat/
Author: UNKNOWN
Author-email: UNKNOWN
License: UNKNOWN
Platform: UNKNOWN
